snbpy_assistant/__init__.py
snbpy_assistant/snbpy_assistant.py
snbpy_assistant-1.0.0.dist-info/LICENSE
snbpy_assistant-1.0.0.dist-info/METADATA
snbpy_assistant-1.0.0.dist-info/WHEEL
snbpy_assistant-1.0.0.dist-info/top_level.txt
snbpy_assistant-1.0.0.dist-info/RECORD
