Metadata-Version: 2.1
Name: snbpy-assistant
Version: 1.0.0
Summary: snbpy
Home-page: https://github.com/chnyangjie/snbpy-assistant
Author: chnyangjie
Author-email: chnyangjie@gmail.com
Project-URL: Bug Reports, https://github.com/chnyangjie/snbpy-assistant/issues
Project-URL: Funding, https://github.com/chnyangjie/snbpy-assistant/issues
Project-URL: Say Thanks!, https://github.com/chnyangjie/snbpy-assistant/issues
Project-URL: Source, https://github.com/chnyangjie/snbpy-assistant/issues
Keywords: snbpy_assistant
Classifier: Development Status :: 3 - Alpha
Classifier: Intended Audience :: Developers
Classifier: Topic :: Software Development :: Build Tools
Classifier: License :: OSI Approved :: MIT License
Classifier: Programming Language :: Python :: 3
Classifier: Programming Language :: Python :: 3.5
Classifier: Programming Language :: Python :: 3.6
Classifier: Programming Language :: Python :: 3.7
Classifier: Programming Language :: Python :: 3.8
Classifier: Programming Language :: Python :: 3 :: Only
Requires-Python: >=3.6, <4
License-File: LICENSE
Requires-Dist: requests
Requires-Dist: snbpy
